README.rst
setup.py
django_forum.egg-info/PKG-INFO
django_forum.egg-info/SOURCES.txt
django_forum.egg-info/dependency_links.txt
django_forum.egg-info/top_level.txt
forum/__init__.py