Metadata-Version: 1.1
Name: django-forum
Version: 0.0.1
Summary: Django forum app
Home-page: https://github.com/dimka665/django-forum
Author: Dmitry Voronin
Author-email: dimka665@gmail.com
License: MIT license
Keywords: django forum reusable app
Platform: UNKNOWN
Classifier: Environment :: Web Environment
Classifier: Intended Audience :: Developers
Classifier: License :: OSI Approved :: MIT License
Classifier: Programming Language :: Python :: 2.7
Classifier: Programming Language :: Python :: 3
Classifier: Programming Language :: Python :: 3.3
Classifier: Topic :: Software Development :: Libraries :: Python Modules
